sunnycheck/_ _init_ _.py
sunnycheck/sunnycheck.py
sunnycheck-0.1.0.dist-info/LICENSE
sunnycheck-0.1.0.dist-info/METADATA
sunnycheck-0.1.0.dist-info/WHEEL
sunnycheck-0.1.0.dist-info/top_level.txt
sunnycheck-0.1.0.dist-info/RECORD
